{
  "description": "Real southeast Missouri ag businesses for Cape Girardeau County demo. At least three vendors per category where possible. Sourced from public listings; verify before outreach.",
  "sources": [
    "https://farmcreditsemo.com",
    "https://www.cropnhail.com",
    "https://extension.missouri.edu/locations/mu-extension-in-cape-girardeau-county",
    "https://semomilling.com",
    "https://www.cgbgrain.com",
    "https://mfajackson.wordpress.com",
    "https://www.davisfarmsupplies.com",
    "https://www.ruralking.com",
    "https://gatewayseed.com",
    "https://www.farmers1stag.com",
    "https://www.bakerimplement.com",
    "https://www.snpartners.com",
    "https://www.jacksoncrop.com",
    "https://www.semolaw.com",
    "https://www.limbaughlaw.com",
    "https://gvseed.com",
    "https://www.aerialcropservices.com"
  ],
  "verified_on": "2026-05-19",
  "vendors": [
    {
      "name": "Farm Credit Southeast Missouri",
      "slug": "farm-credit-southeast-missouri",
      "category": "ag_lender",
      "description": "Farm Credit association serving southeast Missouri with land, operating, and rural home loans. Jackson branch on Washington Street.",
      "website": "https://farmcreditsemo.com",
      "phone": "573-243-4301",
      "street_address": "420 W Washington St",
      "city": "Jackson",
      "state": "MO",
      "region": "central",
      "counties": [
        "Cape Girardeau",
        "Scott",
        "Bollinger",
        "Perry",
        "Stoddard",
        "Mississippi",
        "New Madrid",
        "Dunklin",
        "Pemiscot",
        "Butler",
        "Ripley"
      ],
      "serves_statewide": false,
      "listing_tier": "premium",
      "sponsored": true,
      "active": true,
      "monthly_listing_cents": 49900,
      "billing_notes": "Public listing \u2014 Farm Credit SEMO locations page"
    },
    {
      "name": "FCS Financial",
      "slug": "fcs-financial",
      "category": "ag_lender",
      "description": "Missouri Farm Credit lender for farmland, equipment, livestock, and operating credit. Multiple branches including Jackson.",
      "website": "https://www.myfcsfinancial.com",
      "phone": "855-507-2276",
      "street_address": "420 W Washington St",
      "city": "Jackson",
      "state": "MO",
      "region": "central",
      "counties": [],
      "serves_statewide": true,
      "listing_tier": "featured",
      "sponsored": false,
      "active": true,
      "monthly_listing_cents": 19900,
      "billing_notes": "Statewide ag lender \u2014 verify branch hours locally"
    },
    {
      "name": "MFA Agri Services \u2014 Jackson",
      "slug": "mfa-agri-services-jackson",
      "category": "farm_store_coop",
      "description": "MFA cooperative location offering seed, fertilizer, crop protection, feed, and farm supplies for Cape Girardeau County growers.",
      "website": "https://mfajackson.wordpress.com",
      "phone": "573-243-3549",
      "street_address": "717 S Hope St",
      "city": "Jackson",
      "state": "MO",
      "region": "central",
      "counties": [
        "Cape Girardeau",
        "Scott",
        "Bollinger"
      ],
      "serves_statewide": false,
      "listing_tier": "premium",
      "sponsored": true,
      "active": true,
      "monthly_listing_cents": 39900,
      "billing_notes": "Jackson Chamber / MFA location listing"
    },
    {
      "name": "Coop Service Center",
      "slug": "coop-service-center-whitewater",
      "category": "grain_merchandiser",
      "description": "Grain elevator and cooperative service center in Whitewater (Cape Girardeau County).",
      "phone": "573-794-2211",
      "street_address": "8759 State Highway A",
      "city": "Whitewater",
      "state": "MO",
      "region": "central",
      "counties": [
        "Cape Girardeau"
      ],
      "serves_statewide": false,
      "listing_tier": "standard",
      "sponsored": false,
      "active": true,
      "monthly_listing_cents": 0,
      "billing_notes": "Farm directory listing \u2014 no website found"
    },
    {
      "name": "Consolidated Grain and Barge Co.",
      "slug": "consolidated-grain-barge-scott-city",
      "category": "grain_merchandiser",
      "description": "CGB grain marketing and river terminal operations serving southeast Missouri producers (Scott City / Cape area).",
      "website": "https://www.cgbgrain.com",
      "phone": "573-264-2411",
      "email": "grainmarketing@cgb.com",
      "city": "Scott City",
      "state": "MO",
      "region": "central",
      "counties": [
        "Cape Girardeau",
        "Scott",
        "Bollinger",
        "Perry",
        "Stoddard",
        "Mississippi"
      ],
      "serves_statewide": false,
      "listing_tier": "featured",
      "sponsored": true,
      "active": true,
      "monthly_listing_cents": 24900,
      "billing_notes": "Semo Port / CGB regional contact"
    },
    {
      "name": "SEMO Milling, LLC",
      "slug": "semo-milling",
      "category": "grain_merchandiser",
      "description": "Commercial corn mill and grain receiving near Scott City; publishes cash bids for area growers.",
      "website": "https://semomilling.com",
      "phone": "573-264-4565",
      "street_address": "261 River Rd",
      "city": "Scott City",
      "state": "MO",
      "region": "central",
      "counties": [
        "Cape Girardeau",
        "Scott",
        "Bollinger",
        "Perry",
        "Stoddard",
        "Mississippi"
      ],
      "serves_statewide": false,
      "listing_tier": "standard",
      "sponsored": false,
      "active": true,
      "monthly_listing_cents": 0,
      "billing_notes": "Producer portal hours on semomilling.com"
    },
    {
      "name": "C&H Insurance Services",
      "slug": "c-and-h-insurance-services",
      "category": "crop_insurance",
      "description": "Independent crop and livestock insurance agency serving southeast Missouri (MPCI, hail, LRP, PRF).",
      "website": "https://www.cropnhail.com",
      "phone": "573-683-3800",
      "street_address": "415 E Marshall St",
      "city": "Charleston",
      "state": "MO",
      "region": "central",
      "counties": [
        "Cape Girardeau",
        "Scott",
        "Bollinger",
        "Perry",
        "Stoddard",
        "Mississippi",
        "New Madrid",
        "Dunklin",
        "Pemiscot",
        "Butler",
        "Ripley"
      ],
      "serves_statewide": false,
      "listing_tier": "premium",
      "sponsored": true,
      "active": true,
      "monthly_listing_cents": 34900,
      "billing_notes": "Charleston HQ \u2014 serves Cape Girardeau County farmers"
    },
    {
      "name": "Missouri Farm Bureau Insurance \u2014 Cape Girardeau",
      "slug": "mofb-insurance-cape-girardeau",
      "category": "crop_insurance",
      "description": "Farm Bureau insurance agent office for farm, crop, and property coverage in Cape Girardeau.",
      "website": "https://www.mofb.org",
      "phone": "573-651-3231",
      "street_address": "2504 William St",
      "city": "Cape Girardeau",
      "state": "MO",
      "region": "central",
      "counties": [
        "Cape Girardeau",
        "Scott"
      ],
      "serves_statewide": false,
      "listing_tier": "standard",
      "sponsored": false,
      "active": true,
      "monthly_listing_cents": 0,
      "billing_notes": "Heather Brune agency listing"
    },
    {
      "name": "Farm Risk Advisors \u2014 Jim Hardecke",
      "slug": "farm-risk-advisors-hardecke",
      "category": "crop_insurance",
      "description": "Livestock risk protection, PRF, and crop insurance specialist for Missouri and Midwest producers.",
      "website": "https://farmriskadvisor.com",
      "phone": "573-680-1830",
      "city": "Jackson",
      "state": "MO",
      "region": "central",
      "counties": [
        "Cape Girardeau",
        "Scott",
        "Bollinger",
        "Perry",
        "Stoddard",
        "Mississippi",
        "New Madrid",
        "Dunklin",
        "Pemiscot",
        "Butler",
        "Ripley"
      ],
      "serves_statewide": false,
      "listing_tier": "standard",
      "sponsored": false,
      "active": true,
      "monthly_listing_cents": 0
    },
    {
      "name": "Nutrien Ag Solutions \u2014 Sikeston",
      "slug": "nutrien-ag-solutions-sikeston",
      "category": "fertilizer_chemical",
      "description": "Full-service crop inputs, fertilizer, and crop protection with custom application support (Sikeston location).",
      "website": "https://www.nutrienagsolutions.com",
      "phone": "573-481-9416",
      "street_address": "18267 US Highway 61",
      "city": "Sikeston",
      "state": "MO",
      "latitude": 36.8767,
      "longitude": -89.5854,
      "region": "central",
      "counties": [
        "Cape Girardeau",
        "Scott",
        "Bollinger",
        "Perry",
        "Stoddard",
        "Mississippi",
        "New Madrid"
      ],
      "serves_statewide": false,
      "listing_tier": "featured",
      "sponsored": true,
      "active": true,
      "monthly_listing_cents": 29900
    },
    {
      "name": "Helena Agri-Enterprises \u2014 Clarkton",
      "slug": "helena-agri-clarkton",
      "category": "fertilizer_chemical",
      "description": "Helena location providing agricultural chemicals and crop production products for bootheel and southeast Missouri.",
      "website": "https://www.helenachemical.com",
      "phone": "573-448-5357",
      "city": "Clarkton",
      "state": "MO",
      "region": "central",
      "counties": [
        "Dunklin",
        "New Madrid",
        "Scott",
        "Mississippi",
        "Stoddard"
      ],
      "serves_statewide": false,
      "listing_tier": "standard",
      "sponsored": false,
      "active": true,
      "monthly_listing_cents": 0
    },
    {
      "name": "Delta Growers Association",
      "slug": "delta-growers-association",
      "category": "farm_store_coop",
      "description": "Farmer-owned cooperative with fertilizer, seed, chemicals, fuel, and grain services across southeast Missouri.",
      "website": "https://www.deltagrowers.com",
      "phone": "573-649-3036",
      "city": "Charleston",
      "state": "MO",
      "region": "central",
      "counties": [
        "Mississippi",
        "Scott",
        "New Madrid",
        "Pemiscot",
        "Stoddard"
      ],
      "serves_statewide": false,
      "listing_tier": "featured",
      "sponsored": false,
      "active": true,
      "monthly_listing_cents": 19900,
      "billing_notes": "Verify main office phone on deltagrowers.com",
      "street_address": "313 S Highway 105",
      "email": "info@deltagrowers.com"
    },
    {
      "name": "Rosier Ag Service",
      "slug": "rosier-ag-service",
      "description": "Pioneer seed agency near Mound City serving northwest Missouri and southeast Iowa row-crop farmers.",
      "website": "https://www.rosieragservice.com",
      "phone": "660-442-5372",
      "street_address": "22325 Holt 140",
      "city": "Mound City",
      "counties": [
        "Cape Girardeau",
        "Scott",
        "Perry",
        "Bollinger"
      ],
      "billing_notes": "Pioneer warehouse listing \u2014 rosieragservice.com",
      "category": "seed_dealer",
      "state": "MO",
      "region": "central",
      "serves_statewide": false,
      "listing_tier": "standard",
      "sponsored": false,
      "active": true,
      "monthly_listing_cents": 0
    },
    {
      "name": "Davis Farm Supplies, Inc.",
      "slug": "davis-farm-supplies-jackson",
      "category": "equipment_dealer",
      "description": "Family-owned ag equipment dealer in Jackson since 1955 \u2014 sales, parts, and service.",
      "website": "https://www.davisfarmsupplies.com",
      "phone": "573-243-1300",
      "street_address": "5547 US Highway 61",
      "city": "Jackson",
      "state": "MO",
      "region": "central",
      "counties": [
        "Cape Girardeau",
        "Perry",
        "Bollinger"
      ],
      "serves_statewide": false,
      "listing_tier": "standard",
      "sponsored": false,
      "active": true,
      "monthly_listing_cents": 0
    },
    {
      "name": "McCoy Construction & Forestry",
      "slug": "mccoy-construction-forestry-cape",
      "category": "equipment_dealer",
      "description": "John Deere construction and forestry equipment dealer with parts and service in Cape Girardeau.",
      "website": "https://www.mccoycf.com",
      "phone": "573-334-0563",
      "street_address": "1421 S West End Blvd",
      "city": "Cape Girardeau",
      "state": "MO",
      "region": "central",
      "counties": [
        "Cape Girardeau",
        "Scott",
        "Bollinger",
        "Perry",
        "Stoddard",
        "Mississippi"
      ],
      "serves_statewide": false,
      "listing_tier": "standard",
      "sponsored": false,
      "active": true,
      "monthly_listing_cents": 0
    },
    {
      "name": "Rural King \u2014 Cape Girardeau",
      "slug": "rural-king-cape-girardeau",
      "category": "farm_store_coop",
      "description": "Farm and home store with livestock feed, fencing, tools, and seasonal ag supplies.",
      "website": "https://www.ruralking.com",
      "phone": "573-837-4929",
      "street_address": "210 Silver Springs Rd",
      "city": "Cape Girardeau",
      "state": "MO",
      "region": "central",
      "counties": [
        "Cape Girardeau",
        "Scott"
      ],
      "serves_statewide": false,
      "listing_tier": "standard",
      "sponsored": false,
      "active": true,
      "monthly_listing_cents": 0
    },
    {
      "name": "Extension \u2014 Cape Girardeau County",
      "slug": "mu-extension-cape-girardeau",
      "category": "agronomist",
      "description": "University of Missouri Extension \u2014 soil testing, crop diagnostics, pesticide training, and farm business resources (not a product vendor).",
      "website": "https://extension.missouri.edu/counties/cape-girardeau",
      "phone": "573-243-1606",
      "street_address": "684 Jackson Trail",
      "city": "Jackson",
      "state": "MO",
      "region": "central",
      "counties": [
        "Cape Girardeau"
      ],
      "serves_statewide": false,
      "listing_tier": "standard",
      "sponsored": false,
      "active": true,
      "monthly_listing_cents": 0,
      "billing_notes": "Educational resource \u2014 independent of input sales"
    },
    {
      "category": "custom_applicator",
      "state": "MO",
      "region": "central",
      "counties": [
        "Scott",
        "Cape Girardeau",
        "Stoddard"
      ],
      "serves_statewide": false,
      "listing_tier": "standard",
      "sponsored": false,
      "active": true,
      "monthly_listing_cents": 0,
      "name": "MFA Agri Services \u2014 Chaffee",
      "slug": "mfa-agri-services-chaffee",
      "description": "MFA location known for custom spray and variable-rate fertilizer application in the Bootheel (per MFA/Todays Farmer).",
      "website": "https://mfa-inc.com/store-locator",
      "street_address": "1980 Cummins Dr",
      "city": "Chaffee",
      "billing_notes": "Chaffee Chamber directory \u2014 confirm phone via MFA store locator"
    },
    {
      "name": "Hillin & Company, P.C.",
      "slug": "hillin-and-company-cpa",
      "category": "farm_accounting",
      "description": "Cape Girardeau CPA firm offering tax planning, accounting, and QuickBooks support for businesses and farm operations.",
      "website": "http://www.hillinandcompany.com",
      "phone": "573-334-8200",
      "city": "Cape Girardeau",
      "state": "MO",
      "region": "central",
      "counties": [
        "Cape Girardeau",
        "Scott"
      ],
      "serves_statewide": false,
      "listing_tier": "standard",
      "sponsored": false,
      "active": true,
      "monthly_listing_cents": 0,
      "billing_notes": "hillinandcompany.com"
    },
    {
      "name": "Birk Law Firm",
      "slug": "birk-law-firm",
      "category": "farm_attorney",
      "description": "Cape Girardeau law firm with agricultural law, farm succession, leases, and estate planning for producers.",
      "website": "https://www.birklegal.com",
      "phone": "573-332-8585",
      "street_address": "2851 Professional Ct Ste C",
      "city": "Cape Girardeau",
      "state": "MO",
      "region": "central",
      "counties": [
        "Cape Girardeau",
        "Scott",
        "Bollinger"
      ],
      "serves_statewide": false,
      "listing_tier": "standard",
      "sponsored": false,
      "active": true,
      "monthly_listing_cents": 0,
      "billing_notes": "semolaw.com / birklegal.com agricultural practice"
    },
    {
      "state": "MO",
      "region": "central",
      "serves_statewide": true,
      "listing_tier": "featured",
      "sponsored": false,
      "active": true,
      "monthly_listing_cents": 0,
      "name": "Rabo AgriFinance",
      "slug": "rabo-agrifinance",
      "category": "ag_lender",
      "description": "Missouri-headquartered ag lender offering operating lines, real estate, equipment, and input financing.",
      "website": "https://www.rabobankna.com",
      "phone": "800-772-1140",
      "city": "Chesterfield",
      "counties": []
    },
    {
      "state": "MO",
      "region": "central",
      "serves_statewide": false,
      "listing_tier": "standard",
      "sponsored": false,
      "active": true,
      "monthly_listing_cents": 0,
      "name": "Gateway Seed",
      "slug": "gateway-seed-scott-city",
      "category": "seed_dealer",
      "description": "Scott City-based corn and soybean seed company serving southeast Missouri and the Mid-South since 1997.",
      "website": "https://gatewayseed.com",
      "city": "Scott City",
      "counties": [
        "Cape Girardeau",
        "Scott",
        "Bollinger",
        "Perry",
        "Stoddard",
        "Mississippi",
        "New Madrid"
      ]
    },
    {
      "state": "MO",
      "region": "central",
      "serves_statewide": false,
      "listing_tier": "standard",
      "sponsored": false,
      "active": true,
      "monthly_listing_cents": 0,
      "name": "Sutter Seed Services",
      "slug": "sutter-seed-services",
      "category": "seed_dealer",
      "description": "Family-owned Pioneer seed dealer serving northeast Missouri and the surrounding region.",
      "website": "https://www.sutterseedservicesinc.com",
      "phone": "573-393-2008",
      "street_address": "6220 County Road 306",
      "city": "Taylor",
      "counties": [
        "Clark",
        "Lewis",
        "Marion",
        "Ralls",
        "Pike",
        "Cape Girardeau",
        "Scott"
      ]
    },
    {
      "state": "MO",
      "region": "central",
      "serves_statewide": false,
      "listing_tier": "standard",
      "sponsored": false,
      "active": true,
      "monthly_listing_cents": 0,
      "name": "Green Valley Seed, LLC",
      "slug": "green-valley-seed",
      "category": "seed_dealer",
      "description": "Regional seed distributor in Kahoka with corn, soybean, and forage products for northeast Missouri and nearby counties.",
      "website": "https://gvseed.com",
      "phone": "800-748-7943",
      "street_address": "121 W College St",
      "city": "Kahoka",
      "counties": [
        "Clark",
        "Lewis",
        "Marion",
        "Knox",
        "Scotland",
        "Cape Girardeau",
        "Scott",
        "Perry"
      ]
    },
    {
      "state": "MO",
      "region": "central",
      "serves_statewide": true,
      "listing_tier": "standard",
      "sponsored": false,
      "active": true,
      "monthly_listing_cents": 0,
      "name": "nuWay Ag",
      "slug": "nuway-ag-missouri",
      "category": "fertilizer_chemical",
      "description": "Agricultural spray equipment, parts, and training; supports custom applicators across Missouri.",
      "website": "https://nuwayag.com",
      "phone": "234-271-2767",
      "city": "Dundee",
      "counties": []
    },
    {
      "state": "MO",
      "region": "central",
      "serves_statewide": false,
      "listing_tier": "standard",
      "sponsored": false,
      "active": true,
      "monthly_listing_cents": 0,
      "name": "Jackson Crop Insurance",
      "slug": "jackson-crop-insurance",
      "category": "crop_insurance",
      "description": "Crop hail, MPCI, LRP, and PRF policies with mapping and acreage reporting support.",
      "website": "https://www.jacksoncrop.com",
      "city": "Jackson",
      "counties": [
        "Cape Girardeau",
        "Scott",
        "Bollinger",
        "Perry",
        "Stoddard",
        "Mississippi",
        "New Madrid",
        "Dunklin",
        "Pemiscot",
        "Butler",
        "Ripley",
        "Stoddard"
      ]
    },
    {
      "state": "MO",
      "region": "central",
      "serves_statewide": false,
      "listing_tier": "standard",
      "sponsored": false,
      "active": true,
      "monthly_listing_cents": 0,
      "name": "Baker Implement",
      "slug": "baker-implement-cape",
      "category": "equipment_dealer",
      "description": "CASE IH dealer in Cape Girardeau \u2014 tractors, combines, sprayers, tillage, parts, and service.",
      "website": "https://www.bakerimplement.com",
      "phone": "573-335-8226",
      "street_address": "401 S Kingshighway St",
      "city": "Cape Girardeau",
      "counties": [
        "Cape Girardeau",
        "Scott",
        "Bollinger",
        "Perry",
        "Stoddard",
        "Mississippi"
      ]
    },
    {
      "state": "MO",
      "region": "central",
      "serves_statewide": false,
      "listing_tier": "standard",
      "sponsored": false,
      "active": true,
      "monthly_listing_cents": 0,
      "name": "Sydenstricker Nobbe Partners",
      "slug": "sydenstricker-nobbe-scott-city",
      "category": "equipment_dealer",
      "description": "John Deere dealer in Scott City serving Cape Girardeau and Scott counties since 2002.",
      "website": "https://www.snpartners.com",
      "phone": "573-335-0192",
      "street_address": "1400 E Outer Rd",
      "city": "Scott City",
      "counties": [
        "Cape Girardeau",
        "Scott",
        "Bollinger",
        "Perry",
        "Stoddard",
        "Mississippi"
      ]
    },
    {
      "state": "MO",
      "region": "central",
      "serves_statewide": false,
      "listing_tier": "standard",
      "sponsored": false,
      "active": true,
      "monthly_listing_cents": 0,
      "name": "Tractor Supply \u2014 Cape Girardeau",
      "slug": "tractor-supply-cape",
      "category": "farm_store_coop",
      "description": "Farm and ranch retail for feed, fencing, trailers, tools, and seasonal supplies.",
      "website": "https://www.tractorsupply.com",
      "phone": "573-334-5971",
      "street_address": "501 S Kingshighway St",
      "city": "Cape Girardeau",
      "counties": [
        "Cape Girardeau",
        "Scott"
      ]
    },
    {
      "state": "MO",
      "region": "central",
      "serves_statewide": false,
      "listing_tier": "standard",
      "sponsored": false,
      "active": true,
      "monthly_listing_cents": 0,
      "name": "Farmers 1st Agronomy Services",
      "slug": "farmers-1st-agronomy",
      "category": "agronomist",
      "description": "Independent agronomy company with seed, crop protection, precision ag, and field consulting in the Bootheel.",
      "website": "https://www.farmers1stag.com",
      "phone": "573-360-1974",
      "street_address": "2965 W Highway 80",
      "city": "East Prairie",
      "counties": [
        "Mississippi",
        "Scott",
        "New Madrid",
        "Pemiscot",
        "Stoddard",
        "Cape Girardeau"
      ]
    },
    {
      "state": "MO",
      "region": "central",
      "serves_statewide": false,
      "listing_tier": "standard",
      "sponsored": false,
      "active": true,
      "monthly_listing_cents": 0,
      "name": "Green Valley Seed \u2014 Agronomy Support",
      "slug": "green-valley-seed-agronomy",
      "category": "agronomist",
      "description": "Seed specialists offering product selection and agronomic support for corn, soybeans, and forages.",
      "website": "https://gvseed.com",
      "phone": "800-748-7943",
      "city": "Kahoka",
      "counties": [
        "Clark",
        "Lewis",
        "Scotland",
        "Knox",
        "Cape Girardeau",
        "Scott"
      ]
    },
    {
      "state": "MO",
      "region": "central",
      "serves_statewide": false,
      "listing_tier": "standard",
      "sponsored": false,
      "active": true,
      "monthly_listing_cents": 0,
      "name": "Farmers 1st Agronomy Services \u2014 Application",
      "slug": "farmers-1st-ag-application",
      "category": "custom_applicator",
      "description": "Custom chemical application and precision planting support from the East Prairie location.",
      "website": "https://www.farmers1stag.com",
      "phone": "573-360-1974",
      "street_address": "2965 W Highway 80",
      "city": "East Prairie",
      "counties": [
        "Mississippi",
        "Scott",
        "New Madrid",
        "Pemiscot",
        "Stoddard",
        "Cape Girardeau"
      ]
    },
    {
      "state": "MO",
      "region": "central",
      "serves_statewide": false,
      "listing_tier": "standard",
      "sponsored": false,
      "active": true,
      "monthly_listing_cents": 0,
      "name": "Aerial Crop Services",
      "slug": "aerial-crop-services",
      "category": "custom_applicator",
      "description": "Aerial application of herbicides, insecticides, fungicides, and dry fertilizer in southeast Missouri since 2005.",
      "website": "https://www.aerialcropservices.com",
      "city": "Sikeston",
      "counties": [
        "Cape Girardeau",
        "Scott",
        "Bollinger",
        "Perry",
        "Stoddard",
        "Mississippi",
        "New Madrid",
        "Dunklin",
        "Pemiscot",
        "Butler",
        "Ripley",
        "Stoddard"
      ]
    },
    {
      "state": "MO",
      "region": "central",
      "serves_statewide": false,
      "listing_tier": "standard",
      "sponsored": false,
      "active": true,
      "monthly_listing_cents": 0,
      "name": "Southern Crop Services",
      "slug": "southern-crop-services",
      "category": "custom_applicator",
      "description": "Ground and aerial custom application using precision equipment (southeast Missouri).",
      "website": "https://www.southerncropservices.com",
      "city": "Sikeston",
      "counties": [
        "Scott",
        "Mississippi",
        "New Madrid",
        "Stoddard",
        "Cape Girardeau"
      ]
    },
    {
      "state": "MO",
      "region": "central",
      "serves_statewide": false,
      "listing_tier": "standard",
      "sponsored": false,
      "active": true,
      "monthly_listing_cents": 0,
      "name": "Begley Young Unterreiner White LLC",
      "slug": "begley-young-cpa",
      "category": "farm_accounting",
      "description": "Full-service CPA firm in Cape Girardeau for business owners, executives, and farm tax clients.",
      "website": "https://www.begleycpa.com",
      "phone": "573-334-2845",
      "street_address": "2103 Themis St",
      "city": "Cape Girardeau",
      "counties": [
        "Cape Girardeau",
        "Scott"
      ]
    },
    {
      "state": "MO",
      "region": "central",
      "serves_statewide": false,
      "listing_tier": "standard",
      "sponsored": false,
      "active": true,
      "monthly_listing_cents": 0,
      "name": "Paula Huggins CPA LLC",
      "slug": "paula-huggins-cpa",
      "category": "farm_accounting",
      "description": "Tax preparation, bookkeeping, and payroll with farm Schedule F experience.",
      "website": "https://www.paulahugginscpa.com",
      "phone": "573-339-7676",
      "street_address": "106 S Farrar Dr Ste 102",
      "city": "Cape Girardeau",
      "counties": [
        "Cape Girardeau"
      ]
    },
    {
      "state": "MO",
      "region": "central",
      "serves_statewide": false,
      "listing_tier": "standard",
      "sponsored": false,
      "active": true,
      "monthly_listing_cents": 0,
      "name": "Osburn, Hine & Yates, LLC",
      "slug": "osburn-hine-yates",
      "category": "farm_attorney",
      "description": "Southeast Missouri firm handling agricultural law, land disputes, estate planning, and farm business structure.",
      "website": "https://www.semolaw.com",
      "phone": "573-651-9000",
      "street_address": "3071 Lexington Ave",
      "city": "Cape Girardeau",
      "counties": [
        "Cape Girardeau",
        "Scott",
        "Bollinger",
        "Perry",
        "Stoddard",
        "Mississippi"
      ]
    },
    {
      "state": "MO",
      "region": "central",
      "serves_statewide": false,
      "listing_tier": "standard",
      "sponsored": false,
      "active": true,
      "monthly_listing_cents": 0,
      "name": "The Limbaugh Firm",
      "slug": "limbaugh-law-firm",
      "category": "farm_attorney",
      "description": "Cape Girardeau law firm with agricultural law, leases, tax planning, and agribusiness contracts.",
      "website": "https://www.limbaughlaw.com",
      "phone": "573-335-3316",
      "street_address": "407 N Kingshighway Ste 400",
      "city": "Cape Girardeau",
      "counties": [
        "Cape Girardeau",
        "Scott",
        "Bollinger",
        "Perry",
        "Stoddard",
        "Mississippi"
      ]
    },
    {
      "state": "MO",
      "region": "central",
      "serves_statewide": true,
      "listing_tier": "standard",
      "sponsored": false,
      "active": true,
      "monthly_listing_cents": 0,
      "name": "Farmers Business Network",
      "slug": "farmers-business-network",
      "category": "other",
      "description": "Farmer-to-farmer network for analytics, input price transparency, and grain marketing tools (not a local storefront).",
      "website": "https://www.fbn.com",
      "counties": []
    },
    {
      "state": "MO",
      "region": "central",
      "serves_statewide": false,
      "listing_tier": "standard",
      "sponsored": false,
      "active": true,
      "monthly_listing_cents": 0,
      "name": "Semo Port",
      "slug": "semo-port",
      "category": "other",
      "description": "Regional port authority on the Mississippi River supporting grain barge loading and river logistics near Cape Girardeau.",
      "website": "https://www.semoport.com",
      "city": "Cape Girardeau",
      "counties": [
        "Cape Girardeau",
        "Scott"
      ]
    },
    {
      "state": "MO",
      "region": "central",
      "serves_statewide": false,
      "listing_tier": "standard",
      "sponsored": false,
      "active": true,
      "monthly_listing_cents": 0,
      "name": "USDA Farm Service Agency \u2014 Cape Girardeau County",
      "slug": "usda-fsa-cape-county",
      "category": "other",
      "description": "County FSA office for farm program enrollment, conservation programs, and loan program information (government resource).",
      "website": "https://www.fsa.usda.gov",
      "phone": "573-243-5800",
      "street_address": "684 Jackson Trail",
      "city": "Jackson",
      "counties": [
        "Cape Girardeau"
      ],
      "billing_notes": "Verify FSA office phone on farmers.gov"
    }
  ]
}
